setup.py
QQApp/__init__.py
QQApp/mysdk.py
QQApp.egg-info/PKG-INFO
QQApp.egg-info/SOURCES.txt
QQApp.egg-info/dependency_links.txt
QQApp.egg-info/top_level.txt