Metadata-Version: 1.0
Name: QQApp
Version: 0.0.1
Summary: youlan module
Home-page: UNKNOWN
Author: wmm
Author-email: UNKNOWN
License: UNKNOWN
Platform: UNKNOWN
